erroranalysis/__init__.py
erroranalysis/version.py
erroranalysis/_internal/__init__.py
erroranalysis/_internal/cohort_filter.py
erroranalysis/_internal/constants.py
erroranalysis/_internal/matrix_filter.py
erroranalysis/_internal/metrics.py
erroranalysis/_internal/process_categoricals.py
erroranalysis/_internal/surrogate_error_tree.py
erroranalysis/_internal/utils.py
erroranalysis/_internal/version_checker.py
erroranalysis/_internal/error_analyzer/__init__.py
erroranalysis/_internal/error_report/__init__.py
erroranalysis/analyzer/__init__.py
erroranalysis/analyzer/error_analyzer.py
erroranalysis/error_correlation_methods/__init__.py
erroranalysis/error_correlation_methods/ebm.py
erroranalysis/error_correlation_methods/gbm.py
erroranalysis/report/__init__.py
erroranalysis/report/error_report.py
erroranalysis-0.5.4.dist-info/LICENSE
erroranalysis-0.5.4.dist-info/METADATA
erroranalysis-0.5.4.dist-info/WHEEL
erroranalysis-0.5.4.dist-info/top_level.txt
erroranalysis-0.5.4.dist-info/RECORD
